mtg_kit/cli.py
mtg_kit/models.py
mtg_kit/mtgo/bulk_manage.py
mtg_kit/mtgo/exporter.py
mtg_kit/mtgo/organizer.py
mtg_kit/mtgo/parsers.py
mtg_kit/prices/goatbots.py
mtg_kit/scryfall/prices.py
mtg_kit/scryfall/search.py
mtg_kit/utils.py
mtg_kit-0.1.1.dist-info/METADATA
mtg_kit-0.1.1.dist-info/WHEEL
mtg_kit-0.1.1.dist-info/entry_points.txt
mtg_kit-0.1.1.dist-info/RECORD
