Metadata-Version: 2.1
Name: mtg-kit
Version: 0.1.1
Summary: A collection of tools for Magic the Gathering.
Author: José Aniceto
Author-email: jAniceto@users.noreply.github.com
Requires-Python: >=3.11,<4.0
Classifier: Programming Language :: Python :: 3
Classifier: Programming Language :: Python :: 3.11
Classifier: Programming Language :: Python :: 3.12
Requires-Dist: beautifulsoup4 (>=4.12.3,<5.0.0)
Requires-Dist: pyautogui (>=0.9.54,<0.10.0)
Requires-Dist: requests (>=2.31.0,<3.0.0)
Requires-Dist: sqlalchemy (>=2.0.27,<3.0.0)
Requires-Dist: sqlmodel (>=0.0.16,<0.0.17)
Requires-Dist: tqdm (>=4.66.2,<5.0.0)
Requires-Dist: typer (>=0.9.0,<0.10.0)
